bruce_ircbot-2.0.data/scripts/ircbot
bruce_ircbot-2.0.dist-info/DESCRIPTION.rst
bruce_ircbot-2.0.dist-info/METADATA
bruce_ircbot-2.0.dist-info/RECORD
bruce_ircbot-2.0.dist-info/WHEEL
bruce_ircbot-2.0.dist-info/metadata.json
bruce_ircbot-2.0.dist-info/top_level.txt
plugins/__init__.py
plugins/admin.py
plugins/echo.py
plugins/ip.py
plugins/linkhandler.py
pyircbot/__init__.py
pyircbot/__main__.py
pyircbot/globalvar.py
pyircbot/plugins/__init__.py
pyircbot/plugins/admin.py
pyircbot/plugins/echo.py
pyircbot/plugins/ip.py
pyircbot/plugins/linkhandler.py
